LICENSE
MANIFEST.in
README.rst
requirements.txt
setup.cfg
setup.py
ckanext/__init__.py
ckanext/odi_certificates_view/__init__.py
ckanext/odi_certificates_view/plugin.py
ckanext/odi_certificates_view/templates/package/read.html
ckanext/odi_certificates_view/templates/package/snippets/additional_info.html
ckanext/odi_certificates_view/tests/__init__.py
ckanext/odi_certificates_view/tests/test_plugin.py
ckanext_odi_certificates_view.egg-info/PKG-INFO
ckanext_odi_certificates_view.egg-info/SOURCES.txt
ckanext_odi_certificates_view.egg-info/dependency_links.txt
ckanext_odi_certificates_view.egg-info/entry_points.txt
ckanext_odi_certificates_view.egg-info/namespace_packages.txt
ckanext_odi_certificates_view.egg-info/top_level.txt