Metadata-Version: 1.1
Name: ckanext-odi-certificates-view
Version: 1.0.0
Summary: ODI certificates view
Home-page: https://github.com/mattRedBox/ckanext-odi_certificates_view
Author: mattRedBox
Author-email: matt@redboxresearchdata.com.au
License: AGPL
Keywords: CKAN QCIF ODI-Queensland theodi certificates
Platform: UNKNOWN
Classifier: Development Status :: 4 - Beta
Classifier: License :: OSI Approved :: GNU Affero General Public License v3 or later (AGPLv3+)
Classifier: Programming Language :: Python :: 2.7
